xhp_flow/__init__.py
xhp_flow/nn/__init__.py
xhp_flow/nn/core.py
xhp_flow/utils/__init__.py
xhp_flow/utils/util.py
xhp_flow-0.0.1.dist-info/LICENSE
xhp_flow-0.0.1.dist-info/METADATA
xhp_flow-0.0.1.dist-info/WHEEL
xhp_flow-0.0.1.dist-info/top_level.txt
xhp_flow-0.0.1.dist-info/RECORD
